visualizerai/__init__.py
visualizerai/core.py
visualizerai/llm.py
visualizerai/llm_plot.py
visualizerai/utils.py
visualizerai-0.2.0.dist-info/LICENSE
visualizerai-0.2.0.dist-info/METADATA
visualizerai-0.2.0.dist-info/WHEEL
visualizerai-0.2.0.dist-info/top_level.txt
visualizerai-0.2.0.dist-info/RECORD
