Metadata-Version: 2.2
Name: visualizerai
Version: 0.2.0
Summary: VisualizerAI: natural language to plots with pandas, matplotlib, and Ollama LLM.
Home-page: https://github.com/Saurabh-Zarekar/visualizerai
Author: VisualizerAI authors
Author-email: your_email@example.com
License: MIT
Classifier: Programming Language :: Python :: 3
Classifier: License :: OSI Approved :: MIT License
Classifier: Operating System :: OS Independent
Requires-Python: >=3.7
License-File: LICENSE
Dynamic: author-email
Dynamic: home-page
Dynamic: requires-python
